jinja2_eval/__init__.py
jinja2_eval/_main.py
jinja2_eval/py.typed
jinja2_eval-0.1.2.dist-info/LICENSE
jinja2_eval-0.1.2.dist-info/METADATA
jinja2_eval-0.1.2.dist-info/WHEEL
jinja2_eval-0.1.2.dist-info/RECORD
