Metadata-Version: 2.1
Name: jinja2-eval
Version: 0.1.2
Summary: Jinja2 Extension for getting eval() result.
Home-page: https://github.com/34j/jinja2-eval
License: CC0 1.0 Universal
Author: 34j
Author-email: 34j.95a2p@simplelogin.com
Requires-Python: >=3.8,<4.0
Classifier: Development Status :: 2 - Pre-Alpha
Classifier: Intended Audience :: Developers
Classifier: License :: Other/Proprietary License
Classifier: Natural Language :: English
Classifier: Operating System :: OS Independent
Classifier: Programming Language :: Python :: 3
Classifier: Programming Language :: Python :: 3.8
Classifier: Programming Language :: Python :: 3.9
Classifier: Programming Language :: Python :: 3.10
Classifier: Programming Language :: Python :: 3.11
Classifier: Programming Language :: Python :: 3.12
Classifier: Programming Language :: Python :: 3.13
Classifier: Topic :: Software Development :: Libraries
Requires-Dist: jinja2
Project-URL: Bug Tracker, https://github.com/34j/jinja2-eval/issues
Project-URL: Changelog, https://github.com/34j/jinja2-eval/blob/main/CHANGELOG.md
Project-URL: Documentation, https://jinja2-eval.readthedocs.io
Project-URL: Repository, https://github.com/34j/jinja2-eval
